langplus/__init__.py
langplus/agents/__init__.py
langplus/agents/agent.py
langplus/agents/agent_toolkits/__init__.py
langplus/agents/agent_toolkits/azure_cognitive_services/__init__.py
langplus/agents/agent_toolkits/azure_cognitive_services/toolkit.py
langplus/agents/agent_toolkits/base.py
langplus/agents/agent_toolkits/csv/__init__.py
langplus/agents/agent_toolkits/csv/base.py
langplus/agents/agent_toolkits/file_management/__init__.py
langplus/agents/agent_toolkits/file_management/toolkit.py
langplus/agents/agent_toolkits/gmail/__init__.py
langplus/agents/agent_toolkits/gmail/toolkit.py
langplus/agents/agent_toolkits/jira/__init__.py
langplus/agents/agent_toolkits/jira/toolkit.py
langplus/agents/agent_toolkits/json/__init__.py
langplus/agents/agent_toolkits/json/base.py
langplus/agents/agent_toolkits/json/prompt.py
langplus/agents/agent_toolkits/json/toolkit.py
langplus/agents/agent_toolkits/nla/__init__.py
langplus/agents/agent_toolkits/nla/tool.py
langplus/agents/agent_toolkits/nla/toolkit.py
langplus/agents/agent_toolkits/openapi/__init__.py
langplus/agents/agent_toolkits/openapi/base.py
langplus/agents/agent_toolkits/openapi/planner.py
langplus/agents/agent_toolkits/openapi/planner_prompt.py
langplus/agents/agent_toolkits/openapi/prompt.py
langplus/agents/agent_toolkits/openapi/spec.py
langplus/agents/agent_toolkits/openapi/toolkit.py
langplus/agents/agent_toolkits/pandas/__init__.py
langplus/agents/agent_toolkits/pandas/base.py
langplus/agents/agent_toolkits/pandas/prompt.py
langplus/agents/agent_toolkits/playwright/__init__.py
langplus/agents/agent_toolkits/playwright/toolkit.py
langplus/agents/agent_toolkits/powerbi/__init__.py
langplus/agents/agent_toolkits/powerbi/base.py
langplus/agents/agent_toolkits/powerbi/chat_base.py
langplus/agents/agent_toolkits/powerbi/prompt.py
langplus/agents/agent_toolkits/powerbi/toolkit.py
langplus/agents/agent_toolkits/python/__init__.py
langplus/agents/agent_toolkits/python/base.py
langplus-0.0.196.dist-info/LICENSE
langplus-0.0.196.dist-info/METADATA
langplus-0.0.196.dist-info/WHEEL
langplus-0.0.196.dist-info/entry_points.txt
langplus-0.0.196.dist-info/RECORD
